pxhelper/__init__.py
pxhelper/config.py
pxhelper/downloader.py
pxhelper/ffmpeg.exe
pxhelper/imgfilter.py
pxhelper/login.py
pxhelper/main.py
pxhelper/parser.py
pxhelper/pxelem.py
pxhelper/remuxer.py
pxhelper-0.1.0.dist-info/METADATA
pxhelper-0.1.0.dist-info/RECORD
pxhelper-0.1.0.dist-info/WHEEL
pxhelper-0.1.0.dist-info/entry_points.txt
pxhelper-0.1.0.dist-info/top_level.txt
