Metadata-Version: 2.1
Name: pxhelper
Version: 0.1.0
Summary: Pixiv downloader
Home-page: https://github.com/eternal-flame-AD/px_helper
Author: eternal-flame-AD
Author-email: ef@eternalflame.cn
License: UNKNOWN
Project-URL: Source, https://github.com/eternal-flame-AD/px_helper
Keywords: pixiv
Platform: UNKNOWN
Classifier: Development Status :: 3 - Alpha
Classifier: Intended Audience :: Developers
Classifier: License :: OSI Approved :: MIT License
Classifier: Programming Language :: Python :: 3.6
Classifier: Programming Language :: Python :: 3.7
Requires-Python: >=3.6
Requires-Dist: beautifulsoup4
Requires-Dist: html5lib
Requires-Dist: gevent
